{
  "block_id": "asset_folder_structure",
  "label": "Asset Folder Structure",
  "category": "style/6F_brand_assets",
  "description": "Consistent naming/storage convention",
  "molt_type": "Subject",
  "editable_fields": {
    "content": "Consistent naming/storage convention",
    "style": "design + system",
    "behavior": "visual_logic"
  },
  "bolt_ready": true,
  "export_target": [
    "bolt",
    "pdf"
  ],
  "snap_config": {
    "snap_zone": "bottom",
    "mergeable_with": [],
    "priority": 4
  },
  "runtime_behavior_flags": {
    "is_active": true
  },
  "canto_overlay": {
    "category_code": "CH19",
    "snap_to": [
      "Primary"
    ],
    "fit_score": 0.95
  },
  "cantocore": "GOAL=STYLE, DOMAIN=UI, STYLE=MODULAR",
  "code_modules": [],
  "ledger": {
    "originator": "Christopher L Haynes",
    "verified_by": "PoeUMG",
    "created_at": "AUTO",
    "edit_log": []
  }
}